{
  "_comment": "Sample Investran CRM v2 response. This is what `investran_inbound.py` receives when it calls GET /api/ReferenceData/v2/positions/{positionId}/securities. The Income Calculator's Import JSON button accepts this shape directly — it auto-detects the envelope and maps CRM fields into the internal instrument shape.",
  "_source": "GET https://investranweb-livedev-us.fiscloudservices.com/api/ReferenceData/v2/positions/{positionId}/securities?asOf=2020-03-05",

  "api": "ReferenceData/v2",
  "endpoint": "/positions/{positionId}/securities",
  "traceId": "00-8f3c9a1b2e4d6f78-a1b2c3d4e5f60708-00",

  "legalEntity": {
    "id":         "7f3a1c10-8e4b-4a2d-9f5e-6c0d4b2a1e3f",
    "externalId": 7,
    "name":       "FIS Capital Partners I"
  },

  "deal": {
    "id":   "1a5b9c20-4f8e-4d7c-b2a6-9e3d0c8f7a64",
    "name": "Alliance Manufacturing"
  },

  "position": {
    "id":   "c9e0b2d4-5a3f-4e61-8c7d-0f1e2a3b4c5d",
    "name": "Alliance Manufacturing (Convertible Note)"
  },

  "period": {
    "begin": "2020-01-01",
    "end":   "2020-03-05",
    "last":  "2019-12-31"
  },

  "security": {
    "id":             "alliance",
    "externalId":     "ALLIANCE-2019-CN",
    "name":           "Alliance Manufacturing (Convertible Note)",
    "securityType":   "PrivateDebt",
    "investranType":  "pikNoteFixed",

    "faceValue":      25000000,
    "purchasePrice":  25000000,
    "commitment":     25000000,
    "currency":       "USD",

    "settlementDate": "2019-01-15",
    "maturityDate":   "2020-03-05",

    "dayBasis":                   "ACT/360",
    "accrualFreq":                "daily",
    "accrualDayCountExclusive":   false,
    "paydateDayCountInclusive":   true,
    "interestPreviousDay":        false,

    "coupon": {
      "type":         "Fixed",
      "fixedRate":    0.12,
      "floatingRate": 0.0,
      "spread":       0.0,
      "floor":        null,
      "cap":          null
    },

    "pik": {
      "enabled":                 true,
      "rate":                    0.14,
      "capitalizationFrequency": "Monthly"
    },

    "nonUseFee": {
      "enabled": false,
      "rate":    0.0
    },

    "principalRepayment": "AtMaturity",
    "principalSchedule": [
      { "date": "2019-01-15", "type": "initial", "amount": 25000000 }
    ],

    "amortization": {
      "method":         "none",
      "startDate":      null,
      "endDate":        null,
      "spread":         0.0,
      "yieldOverride":  null
    },

    "holidayCalendar": "none",
    "skipHolidays":    false
  }
}
